mdbh/__init__.py
mdbh/_version.py
mdbh/caching.py
mdbh/core.py
mdbh/data.py
mdbh/environ.py
mdbh/plot.py
mdbh/sacred.py
mdbh-0.5.dist-info/AUTHORS
mdbh-0.5.dist-info/LICENSE
mdbh-0.5.dist-info/METADATA
mdbh-0.5.dist-info/WHEEL
mdbh-0.5.dist-info/top_level.txt
mdbh-0.5.dist-info/zip-safe
mdbh-0.5.dist-info/RECORD
