Metadata-Version: 2.1
Name: mdbh
Version: 0.5
Summary: A MongoDB, Sacred, and Omniboard helper.
Home-page: https://gitlab.com/MaxSchambach/mdbh
Author: Maximilian Schambach
Author-email: schambach@kit.edu
License: GNU General Public License v3 (GPLv3)
Platform: UNKNOWN
Classifier: Programming Language :: Python :: 3.8
Classifier: Programming Language :: Python :: 3.9
Classifier: License :: OSI Approved :: GNU General Public License v3 (GPLv3)
Classifier: Operating System :: OS Independent
Classifier: Development Status :: 4 - Beta
Requires-Python: >=3.8
Requires-Dist: pymongo (>=3.0)
Requires-Dist: pandas
Requires-Dist: stopit (>=1.1.2)
Provides-Extra: plot
Requires-Dist: numpy ; extra == 'plot'
Requires-Dist: matplotlib ; extra == 'plot'
